LICENSE
MANIFEST.in
README.MD
README.md
setup.cfg
setup.py
simple_orthanc/__init__.py
simple_orthanc/api.py
simple_orthanc/constants.py
simple_orthanc/dicom_tags.py
simple_orthanc/helpers.py
simple_orthanc/image.py
simple_orthanc/interface.py
simple_orthanc/logger.py
simple_orthanc/orthanc.py
simple_orthanc/test.py
simple_orthanc.egg-info/PKG-INFO
simple_orthanc.egg-info/SOURCES.txt
simple_orthanc.egg-info/dependency_links.txt
simple_orthanc.egg-info/not-zip-safe
simple_orthanc.egg-info/requires.txt
simple_orthanc.egg-info/top_level.txt