Metadata-Version: 2.1
Name: simple-orthanc
Version: 0.9.9.4
Summary: Pythonic interface to access DICOM data on an Orthanc Server
Home-page: UNKNOWN
Author: M. Segbers
Author-email: msegbers@gmail.com
License: MIT
Keywords: image images orthanc simpleitk medical dicom
Platform: UNKNOWN
Classifier: Development Status :: 3 - Alpha
Classifier: License :: OSI Approved :: MIT License
Classifier: Programming Language :: Python :: 3.6
Classifier: Topic :: Scientific/Engineering :: Medical Science Apps.
Classifier: Intended Audience :: Science/Research
Classifier: Natural Language :: English
Provides-Extra: SimpleITK
Provides-Extra: Viewer
License-File: LICENSE
